autobackup/__init__.py
autobackup/_modidx.py
autobackup/core.py
autobackup-0.0.4.dist-info/LICENSE
autobackup-0.0.4.dist-info/METADATA
autobackup-0.0.4.dist-info/WHEEL
autobackup-0.0.4.dist-info/entry_points.txt
autobackup-0.0.4.dist-info/top_level.txt
autobackup-0.0.4.dist-info/RECORD
